.DS_Store
yt_streams-0.1.0.dist-info/METADATA
yt_streams-0.1.0.dist-info/WHEEL
yt_streams-0.1.0.dist-info/entry_points.txt
yt_streams/__init__.py
yt_streams/airflow/__init__.py
yt_streams/airflow/tasks.py
yt_streams/airflow/yt_streams_catalog.py
yt_streams/cli.py
yt_streams/config.py
yt_streams/control.py
yt_streams/controller.py
yt_streams/http_client.py
yt_streams/meta.py
yt_streams/models.py
yt_streams/proxy_manager.py
yt_streams/ratelimit.py
yt_streams/robots_config.py
yt_streams/stealth.py
yt_streams/storage.py
yt_streams/streamui/__init__.py
yt_streams/streamui/app.py
yt_streams/streamui/components/__init__.py
yt_streams/streamui/components/catalog.py
yt_streams/streamui/components/config.py
yt_streams/streamui/components/controls.py
yt_streams/streamui/components/errors.py
yt_streams/streamui/components/ledger.py
yt_streams/streamui/components/schedules.py
yt_streams/streamui/components/schedules_viz.py
yt_streams/streamui/components/utils.py
yt_streams/streamui/components/workers.py
yt_streams/streamui/state.py
yt_streams/tui.py
yt_streams/url_handler.py
yt_streams/worker.py
yt_streams-0.1.0.dist-info/RECORD
