Metadata-Version: 2.1
Name: yt_streams
Version: 0.1.0
Summary: Multi-session YouTube runner with scheduling, TUI/Streamlit dashboards, and logging.
Keywords: youtube,playwright,streamlit,textual,apscheduler,yt-dlp
License: MIT
Requires-Python: ==3.13.*
Requires-Dist: pydantic>=2.12.0
Requires-Dist: pydantic-settings>=2.11.0
Requires-Dist: yt-dlp>=2025.9.26
Requires-Dist: textual>=6.2.1
Requires-Dist: playwright>=1.55.0
Requires-Dist: playwright-stealth>=1.0.6
Requires-Dist: apscheduler>=3.10.4
Requires-Dist: typer>=0.12.5
Requires-Dist: streamlit>=1.50.0
Requires-Dist: pandas>=2.3.3
Requires-Dist: pyarrow>=17.0.0
Requires-Dist: fake-useragent>=1.4.0
Requires-Dist: httpx>=0.27.0
Requires-Dist: curl-cffi>=0.7.0
Requires-Dist: cloudscraper>=1.2.71
Requires-Dist: undetected-chromedriver>=3.5.5
Requires-Dist: selenium-stealth>=1.0.6
Requires-Dist: selenium>=4.15.0
Requires-Dist: requests>=2.31.0
Requires-Dist: beautifulsoup4>=4.12.0
Requires-Dist: python-dotenv>=1.0.0
Requires-Dist: aiofiles>=23.0.0
Requires-Dist: rich>=14.2.0
Requires-Dist: watchdog>=6.0.0
Provides-Extra: viz
Requires-Dist: plotly>=6.3.1; extra == "viz"
Provides-Extra: airflow
Requires-Dist: apache-airflow>=3.1.0; extra == "airflow"
